elcomecu/__init__.py
elcomecu/__main__.py
elcomecu/receipt.py
elcomecu-0.1.1.dist-info/METADATA
elcomecu-0.1.1.dist-info/WHEEL
elcomecu-0.1.1.dist-info/top_level.txt
elcomecu-0.1.1.dist-info/RECORD
