Metadata-Version: 2.1
Name: elcomecu
Version: 0.1.1
Summary: Пакет для генерации чеков на основе данных о заказах
Author-email: Savva Serebriakov <savva08savva08@gmail.com>
License: MIT
Requires-Python: >=3.8
Requires-Dist: pandas==2.2.2
